<?xml version="1.0" encoding="utf-8"?>
<annotations>
  <version>1.1</version>
  <meta>
    <task>
      <id>1721566</id>
      <name>uppercut_13</name>
      <size>6625</size>
      <mode>interpolation</mode>
      <overlap>5</overlap>
      <bugtracker></bugtracker>
      <created>2025-10-24 13:05:46.954611+00:00</created>
      <updated>2025-10-24 13:20:44.030086+00:00</updated>
      <subset>default</subset>
      <start_frame>0</start_frame>
      <stop_frame>6624</stop_frame>
      <frame_filter></frame_filter>
      <segments>
        <segment>
          <id>3159532</id>
          <start>0</start>
          <stop>6624</stop>
          <url>https://app.cvat.ai/api/jobs/3158115</url>
        </segment>
      </segments>
      <owner>
        <username>yu_yen</username>
        <email>yycyenn@gmail.com</email>
      </owner>
      <assignee></assignee>
      <labels>
        <label>
          <name>cross</name>
          <color>#731c07</color>
          <type>any</type>
          <attributes>
          </attributes>
        </label>
        <label>
          <name>uppercut</name>
          <color>#1d8837</color>
          <type>any</type>
          <attributes>
          </attributes>
        </label>
      </labels>
      <original_size>
        <width>1920</width>
        <height>1080</height>
      </original_size>
      <source>Rear Uppercut to the Body ｜ Great for Southpaws.mp4</source>
    </task>
    <dumped>2025-10-24 13:21:27.237357+00:00</dumped>
  </meta>
  <track id="0" label="uppercut" source="manual">
    <box frame="5554" keyframe="1" outside="0" occluded="0" xtl="456.46" ytl="47.87" xbr="954.51" ybr="1080.00" z_order="0">
    </box>
    <box frame="5555" keyframe="0" outside="0" occluded="0" xtl="456.46" ytl="50.06" xbr="956.70" ybr="1080.00" z_order="0">
    </box>
    <box frame="5556" keyframe="0" outside="0" occluded="0" xtl="456.46" ytl="52.25" xbr="958.88" ybr="1080.00" z_order="0">
    </box>
    <box frame="5557" keyframe="0" outside="0" occluded="0" xtl="456.46" ytl="54.44" xbr="961.07" ybr="1080.00" z_order="0">
    </box>
    <box frame="5558" keyframe="0" outside="0" occluded="0" xtl="456.46" ytl="56.63" xbr="963.25" ybr="1080.00" z_order="0">
    </box>
    <box frame="5559" keyframe="0" outside="0" occluded="0" xtl="456.46" ytl="58.82" xbr="965.44" ybr="1080.00" z_order="0">
    </box>
    <box frame="5560" keyframe="0" outside="0" occluded="0" xtl="456.46" ytl="61.00" xbr="967.63" ybr="1080.00" z_order="0">
    </box>
    <box frame="5561" keyframe="0" outside="0" occluded="0" xtl="456.46" ytl="63.19" xbr="969.81" ybr="1080.00" z_order="0">
    </box>
    <box frame="5562" keyframe="0" outside="0" occluded="0" xtl="456.46" ytl="65.38" xbr="972.00" ybr="1080.00" z_order="0">
    </box>
    <box frame="5563" keyframe="0" outside="0" occluded="0" xtl="456.46" ytl="67.57" xbr="974.18" ybr="1080.00" z_order="0">
    </box>
    <box frame="5564" keyframe="0" outside="0" occluded="0" xtl="456.46" ytl="69.76" xbr="976.37" ybr="1080.00" z_order="0">
    </box>
    <box frame="5565" keyframe="0" outside="0" occluded="0" xtl="456.46" ytl="71.95" xbr="978.56" ybr="1080.00" z_order="0">
    </box>
    <box frame="5566" keyframe="0" outside="0" occluded="0" xtl="456.46" ytl="74.13" xbr="980.74" ybr="1080.00" z_order="0">
    </box>
    <box frame="5567" keyframe="0" outside="0" occluded="0" xtl="456.46" ytl="76.32" xbr="982.93" ybr="1080.00" z_order="0">
    </box>
    <box frame="5568" keyframe="0" outside="0" occluded="0" xtl="456.46" ytl="78.51" xbr="985.11" ybr="1080.00" z_order="0">
    </box>
    <box frame="5569" keyframe="1" outside="0" occluded="0" xtl="456.46" ytl="80.70" xbr="987.30" ybr="1080.00" z_order="0">
    </box>
    <box frame="5570" keyframe="1" outside="0" occluded="0" xtl="426.60" ytl="92.60" xbr="1026.10" ybr="1080.00" z_order="0">
    </box>
    <box frame="5571" keyframe="0" outside="0" occluded="0" xtl="426.60" ytl="92.60" xbr="1007.45" ybr="1080.00" z_order="0">
    </box>
    <box frame="5572" keyframe="0" outside="0" occluded="0" xtl="426.60" ytl="92.60" xbr="988.80" ybr="1080.00" z_order="0">
    </box>
    <box frame="5573" keyframe="0" outside="0" occluded="0" xtl="426.60" ytl="92.60" xbr="970.15" ybr="1080.00" z_order="0">
    </box>
    <box frame="5574" keyframe="1" outside="0" occluded="0" xtl="426.60" ytl="92.60" xbr="951.50" ybr="1080.00" z_order="0">
    </box>
    <box frame="5575" keyframe="0" outside="0" occluded="0" xtl="426.60" ytl="87.24" xbr="951.50" ybr="1080.00" z_order="0">
    </box>
    <box frame="5576" keyframe="0" outside="0" occluded="0" xtl="426.60" ytl="81.88" xbr="951.50" ybr="1080.00" z_order="0">
    </box>
    <box frame="5577" keyframe="0" outside="0" occluded="0" xtl="426.60" ytl="76.52" xbr="951.50" ybr="1080.00" z_order="0">
    </box>
    <box frame="5578" keyframe="0" outside="0" occluded="0" xtl="426.60" ytl="71.16" xbr="951.50" ybr="1080.00" z_order="0">
    </box>
    <box frame="5579" keyframe="1" outside="0" occluded="0" xtl="426.60" ytl="65.80" xbr="951.50" ybr="1080.00" z_order="0">
    </box>
    <box frame="5580" keyframe="0" outside="0" occluded="0" xtl="418.40" ytl="65.80" xbr="932.12" ybr="1080.00" z_order="0">
    </box>
    <box frame="5581" keyframe="0" outside="0" occluded="0" xtl="410.20" ytl="65.80" xbr="912.75" ybr="1080.00" z_order="0">
    </box>
    <box frame="5582" keyframe="0" outside="0" occluded="0" xtl="402.00" ytl="65.80" xbr="893.38" ybr="1080.00" z_order="0">
    </box>
    <box frame="5583" keyframe="1" outside="0" occluded="0" xtl="393.80" ytl="65.80" xbr="874.00" ybr="1080.00" z_order="0">
    </box>
    <box frame="5584" keyframe="0" outside="0" occluded="0" xtl="393.80" ytl="65.80" xbr="874.00" ybr="1080.00" z_order="0">
    </box>
    <box frame="5585" keyframe="0" outside="0" occluded="0" xtl="393.80" ytl="65.80" xbr="874.00" ybr="1080.00" z_order="0">
    </box>
    <box frame="5586" keyframe="1" outside="1" occluded="0" xtl="393.80" ytl="65.80" xbr="874.00" ybr="1080.00" z_order="0">
    </box>
  </track>
</annotations>
