<?xml version="1.0" encoding="utf-8"?>
<annotations>
  <version>1.1</version>
  <meta>
    <task>
      <id>1821006</id>
      <name>uppercut_11</name>
      <size>8063</size>
      <mode>interpolation</mode>
      <overlap>5</overlap>
      <bugtracker></bugtracker>
      <created>2025-11-28 08:46:13.813521+00:00</created>
      <updated>2025-11-28 08:54:33.079823+00:00</updated>
      <subset>default</subset>
      <start_frame>0</start_frame>
      <stop_frame>8062</stop_frame>
      <frame_filter></frame_filter>
      <segments>
        <segment>
          <id>3322628</id>
          <start>0</start>
          <stop>8062</stop>
          <url>https://app.cvat.ai/api/jobs/3321277</url>
        </segment>
      </segments>
      <owner>
        <username>yu_yen</username>
        <email>yycyenn@gmail.com</email>
      </owner>
      <assignee></assignee>
      <labels>
        <label>
          <name>cross</name>
          <color>#731c07</color>
          <type>any</type>
          <attributes>
          </attributes>
        </label>
        <label>
          <name>uppercut</name>
          <color>#1d8837</color>
          <type>any</type>
          <attributes>
          </attributes>
        </label>
      </labels>
      <original_size>
        <width>1920</width>
        <height>1080</height>
      </original_size>
      <source>uppercut_11.mp4</source>
    </task>
    <dumped>2025-11-28 08:54:53.150033+00:00</dumped>
  </meta>
  <track id="0" label="uppercut" source="manual">
    <box frame="1224" keyframe="1" outside="0" occluded="0" xtl="793.50" ytl="131.27" xbr="1127.04" ybr="1056.09" z_order="0">
    </box>
    <box frame="1225" keyframe="0" outside="0" occluded="0" xtl="787.02" ytl="127.10" xbr="1136.30" ybr="1056.09" z_order="0">
    </box>
    <box frame="1226" keyframe="0" outside="0" occluded="0" xtl="780.55" ytl="122.93" xbr="1145.57" ybr="1056.09" z_order="0">
    </box>
    <box frame="1227" keyframe="0" outside="0" occluded="0" xtl="774.07" ytl="118.77" xbr="1154.83" ybr="1056.09" z_order="0">
    </box>
    <box frame="1228" keyframe="1" outside="0" occluded="0" xtl="767.60" ytl="114.60" xbr="1164.10" ybr="1056.09" z_order="0">
    </box>
    <box frame="1229" keyframe="0" outside="0" occluded="0" xtl="765.46" ytl="114.60" xbr="1164.10" ybr="1056.09" z_order="0">
    </box>
    <box frame="1230" keyframe="0" outside="0" occluded="0" xtl="763.32" ytl="114.60" xbr="1164.10" ybr="1056.09" z_order="0">
    </box>
    <box frame="1231" keyframe="0" outside="0" occluded="0" xtl="761.18" ytl="114.60" xbr="1164.10" ybr="1056.09" z_order="0">
    </box>
    <box frame="1232" keyframe="0" outside="0" occluded="0" xtl="759.05" ytl="114.60" xbr="1164.10" ybr="1056.09" z_order="0">
    </box>
    <box frame="1233" keyframe="0" outside="0" occluded="0" xtl="756.91" ytl="114.60" xbr="1164.10" ybr="1056.09" z_order="0">
    </box>
    <box frame="1234" keyframe="0" outside="0" occluded="0" xtl="754.77" ytl="114.60" xbr="1164.10" ybr="1056.09" z_order="0">
    </box>
    <box frame="1235" keyframe="0" outside="0" occluded="0" xtl="752.63" ytl="114.60" xbr="1164.10" ybr="1056.09" z_order="0">
    </box>
    <box frame="1236" keyframe="0" outside="0" occluded="0" xtl="750.49" ytl="114.60" xbr="1164.10" ybr="1056.09" z_order="0">
    </box>
    <box frame="1237" keyframe="0" outside="0" occluded="0" xtl="748.35" ytl="114.60" xbr="1164.10" ybr="1056.09" z_order="0">
    </box>
    <box frame="1238" keyframe="0" outside="0" occluded="0" xtl="746.22" ytl="114.60" xbr="1164.10" ybr="1056.09" z_order="0">
    </box>
    <box frame="1239" keyframe="0" outside="0" occluded="0" xtl="744.08" ytl="114.60" xbr="1164.10" ybr="1056.09" z_order="0">
    </box>
    <box frame="1240" keyframe="0" outside="0" occluded="0" xtl="741.94" ytl="114.60" xbr="1164.10" ybr="1056.09" z_order="0">
    </box>
    <box frame="1241" keyframe="1" outside="0" occluded="0" xtl="739.80" ytl="114.60" xbr="1164.10" ybr="1056.09" z_order="0">
    </box>
    <box frame="1242" keyframe="0" outside="0" occluded="0" xtl="739.80" ytl="114.36" xbr="1164.10" ybr="1056.09" z_order="0">
    </box>
    <box frame="1243" keyframe="0" outside="0" occluded="0" xtl="739.80" ytl="114.12" xbr="1164.10" ybr="1056.09" z_order="0">
    </box>
    <box frame="1244" keyframe="0" outside="0" occluded="0" xtl="739.80" ytl="113.88" xbr="1164.10" ybr="1056.09" z_order="0">
    </box>
    <box frame="1245" keyframe="0" outside="0" occluded="0" xtl="739.80" ytl="113.63" xbr="1164.10" ybr="1056.09" z_order="0">
    </box>
    <box frame="1246" keyframe="0" outside="0" occluded="0" xtl="739.80" ytl="113.39" xbr="1164.10" ybr="1056.09" z_order="0">
    </box>
    <box frame="1247" keyframe="0" outside="0" occluded="0" xtl="739.80" ytl="113.15" xbr="1164.10" ybr="1056.09" z_order="0">
    </box>
    <box frame="1248" keyframe="0" outside="0" occluded="0" xtl="739.80" ytl="112.91" xbr="1164.10" ybr="1056.09" z_order="0">
    </box>
    <box frame="1249" keyframe="0" outside="0" occluded="0" xtl="739.80" ytl="112.67" xbr="1164.10" ybr="1056.09" z_order="0">
    </box>
    <box frame="1250" keyframe="0" outside="0" occluded="0" xtl="739.80" ytl="112.43" xbr="1164.10" ybr="1056.09" z_order="0">
    </box>
    <box frame="1251" keyframe="0" outside="0" occluded="0" xtl="739.80" ytl="112.19" xbr="1164.10" ybr="1056.09" z_order="0">
    </box>
    <box frame="1252" keyframe="0" outside="0" occluded="0" xtl="739.80" ytl="111.95" xbr="1164.10" ybr="1056.09" z_order="0">
    </box>
    <box frame="1253" keyframe="0" outside="0" occluded="0" xtl="739.80" ytl="111.70" xbr="1164.10" ybr="1056.09" z_order="0">
    </box>
    <box frame="1254" keyframe="0" outside="0" occluded="0" xtl="739.80" ytl="111.46" xbr="1164.10" ybr="1056.09" z_order="0">
    </box>
    <box frame="1255" keyframe="0" outside="0" occluded="0" xtl="739.80" ytl="111.22" xbr="1164.10" ybr="1056.09" z_order="0">
    </box>
    <box frame="1256" keyframe="0" outside="0" occluded="0" xtl="739.80" ytl="110.98" xbr="1164.10" ybr="1056.09" z_order="0">
    </box>
    <box frame="1257" keyframe="0" outside="0" occluded="0" xtl="739.80" ytl="110.74" xbr="1164.10" ybr="1056.09" z_order="0">
    </box>
    <box frame="1258" keyframe="0" outside="0" occluded="0" xtl="739.80" ytl="110.50" xbr="1164.10" ybr="1056.09" z_order="0">
    </box>
    <box frame="1259" keyframe="0" outside="0" occluded="0" xtl="739.80" ytl="110.26" xbr="1164.10" ybr="1056.09" z_order="0">
    </box>
    <box frame="1260" keyframe="0" outside="0" occluded="0" xtl="739.80" ytl="110.01" xbr="1164.10" ybr="1056.09" z_order="0">
    </box>
    <box frame="1261" keyframe="0" outside="0" occluded="0" xtl="739.80" ytl="109.77" xbr="1164.10" ybr="1056.09" z_order="0">
    </box>
    <box frame="1262" keyframe="0" outside="0" occluded="0" xtl="739.80" ytl="109.53" xbr="1164.10" ybr="1056.09" z_order="0">
    </box>
    <box frame="1263" keyframe="0" outside="0" occluded="0" xtl="739.80" ytl="109.29" xbr="1164.10" ybr="1056.09" z_order="0">
    </box>
    <box frame="1264" keyframe="0" outside="0" occluded="0" xtl="739.80" ytl="109.05" xbr="1164.10" ybr="1056.09" z_order="0">
    </box>
    <box frame="1265" keyframe="0" outside="0" occluded="0" xtl="739.80" ytl="108.81" xbr="1164.10" ybr="1056.09" z_order="0">
    </box>
    <box frame="1266" keyframe="0" outside="0" occluded="0" xtl="739.80" ytl="108.57" xbr="1164.10" ybr="1056.09" z_order="0">
    </box>
    <box frame="1267" keyframe="0" outside="0" occluded="0" xtl="739.80" ytl="108.33" xbr="1164.10" ybr="1056.09" z_order="0">
    </box>
    <box frame="1268" keyframe="0" outside="0" occluded="0" xtl="739.80" ytl="108.08" xbr="1164.10" ybr="1056.09" z_order="0">
    </box>
    <box frame="1269" keyframe="0" outside="0" occluded="0" xtl="739.80" ytl="107.84" xbr="1164.10" ybr="1056.09" z_order="0">
    </box>
    <box frame="1270" keyframe="0" outside="0" occluded="0" xtl="739.80" ytl="107.60" xbr="1164.10" ybr="1056.09" z_order="0">
    </box>
    <box frame="1271" keyframe="0" outside="0" occluded="0" xtl="739.80" ytl="107.36" xbr="1164.10" ybr="1056.09" z_order="0">
    </box>
    <box frame="1272" keyframe="0" outside="0" occluded="0" xtl="739.80" ytl="107.12" xbr="1164.10" ybr="1056.09" z_order="0">
    </box>
    <box frame="1273" keyframe="0" outside="0" occluded="0" xtl="739.80" ytl="106.88" xbr="1164.10" ybr="1056.09" z_order="0">
    </box>
    <box frame="1274" keyframe="0" outside="0" occluded="0" xtl="739.80" ytl="106.64" xbr="1164.10" ybr="1056.09" z_order="0">
    </box>
    <box frame="1275" keyframe="0" outside="0" occluded="0" xtl="739.80" ytl="106.40" xbr="1164.10" ybr="1056.09" z_order="0">
    </box>
    <box frame="1276" keyframe="0" outside="0" occluded="0" xtl="739.80" ytl="106.15" xbr="1164.10" ybr="1056.09" z_order="0">
    </box>
    <box frame="1277" keyframe="0" outside="0" occluded="0" xtl="739.80" ytl="105.91" xbr="1164.10" ybr="1056.09" z_order="0">
    </box>
    <box frame="1278" keyframe="0" outside="0" occluded="0" xtl="739.80" ytl="105.67" xbr="1164.10" ybr="1056.09" z_order="0">
    </box>
    <box frame="1279" keyframe="0" outside="0" occluded="0" xtl="739.80" ytl="105.43" xbr="1164.10" ybr="1056.09" z_order="0">
    </box>
    <box frame="1280" keyframe="0" outside="0" occluded="0" xtl="739.80" ytl="105.19" xbr="1164.10" ybr="1056.09" z_order="0">
    </box>
    <box frame="1281" keyframe="0" outside="0" occluded="0" xtl="739.80" ytl="104.95" xbr="1164.10" ybr="1056.09" z_order="0">
    </box>
    <box frame="1282" keyframe="0" outside="0" occluded="0" xtl="739.80" ytl="104.71" xbr="1164.10" ybr="1056.09" z_order="0">
    </box>
    <box frame="1283" keyframe="0" outside="0" occluded="0" xtl="739.80" ytl="104.47" xbr="1164.10" ybr="1056.09" z_order="0">
    </box>
    <box frame="1284" keyframe="0" outside="0" occluded="0" xtl="739.80" ytl="104.22" xbr="1164.10" ybr="1056.09" z_order="0">
    </box>
    <box frame="1285" keyframe="0" outside="0" occluded="0" xtl="739.80" ytl="103.98" xbr="1164.10" ybr="1056.09" z_order="0">
    </box>
    <box frame="1286" keyframe="0" outside="0" occluded="0" xtl="739.80" ytl="103.74" xbr="1164.10" ybr="1056.09" z_order="0">
    </box>
    <box frame="1287" keyframe="1" outside="1" occluded="0" xtl="739.80" ytl="103.50" xbr="1164.10" ybr="1056.09" z_order="0">
    </box>
  </track>
  <track id="1" label="uppercut" source="manual">
    <box frame="4197" keyframe="1" outside="0" occluded="0" xtl="827.50" ytl="101.89" xbr="1343.88" ybr="1080.00" z_order="0">
    </box>
    <box frame="4198" keyframe="0" outside="0" occluded="0" xtl="827.50" ytl="112.99" xbr="1343.88" ybr="1080.00" z_order="0">
    </box>
    <box frame="4199" keyframe="0" outside="0" occluded="0" xtl="827.50" ytl="124.10" xbr="1343.88" ybr="1080.00" z_order="0">
    </box>
    <box frame="4200" keyframe="1" outside="0" occluded="0" xtl="827.50" ytl="135.20" xbr="1343.88" ybr="1080.00" z_order="0">
    </box>
    <box frame="4201" keyframe="0" outside="0" occluded="0" xtl="827.50" ytl="126.57" xbr="1350.66" ybr="1080.00" z_order="0">
    </box>
    <box frame="4202" keyframe="0" outside="0" occluded="0" xtl="827.50" ytl="117.93" xbr="1357.43" ybr="1080.00" z_order="0">
    </box>
    <box frame="4203" keyframe="1" outside="0" occluded="0" xtl="827.50" ytl="109.30" xbr="1364.20" ybr="1080.00" z_order="0">
    </box>
    <box frame="4204" keyframe="1" outside="0" occluded="0" xtl="827.50" ytl="109.30" xbr="1449.30" ybr="1080.00" z_order="0">
    </box>
    <box frame="4205" keyframe="1" outside="0" occluded="0" xtl="827.50" ytl="109.30" xbr="1525.20" ybr="1080.00" z_order="0">
    </box>
    <box frame="4206" keyframe="0" outside="0" occluded="0" xtl="823.32" ytl="109.30" xbr="1518.75" ybr="1080.00" z_order="0">
    </box>
    <box frame="4207" keyframe="1" outside="0" occluded="0" xtl="819.15" ytl="109.30" xbr="1512.30" ybr="1080.00" z_order="0">
    </box>
    <box frame="4208" keyframe="0" outside="0" occluded="0" xtl="814.97" ytl="109.30" xbr="1494.70" ybr="1080.00" z_order="0">
    </box>
    <box frame="4209" keyframe="1" outside="0" occluded="0" xtl="810.80" ytl="109.30" xbr="1477.10" ybr="1080.00" z_order="0">
    </box>
    <box frame="4210" keyframe="1" outside="0" occluded="0" xtl="810.80" ytl="109.30" xbr="1412.30" ybr="1080.00" z_order="0">
    </box>
    <box frame="4211" keyframe="1" outside="0" occluded="0" xtl="810.80" ytl="109.30" xbr="1358.60" ybr="1080.00" z_order="0">
    </box>
    <box frame="4212" keyframe="1" outside="0" occluded="0" xtl="810.80" ytl="109.30" xbr="1316.00" ybr="1080.00" z_order="0">
    </box>
    <box frame="4213" keyframe="0" outside="0" occluded="0" xtl="810.80" ytl="100.95" xbr="1316.00" ybr="1080.00" z_order="0">
    </box>
    <box frame="4214" keyframe="1" outside="0" occluded="0" xtl="810.80" ytl="92.60" xbr="1316.00" ybr="1080.00" z_order="0">
    </box>
    <box frame="4215" keyframe="0" outside="0" occluded="0" xtl="810.80" ytl="92.60" xbr="1316.00" ybr="1080.00" z_order="0">
    </box>
    <box frame="4216" keyframe="0" outside="0" occluded="0" xtl="810.80" ytl="92.60" xbr="1316.00" ybr="1080.00" z_order="0">
    </box>
    <box frame="4217" keyframe="0" outside="0" occluded="0" xtl="810.80" ytl="92.60" xbr="1316.00" ybr="1080.00" z_order="0">
    </box>
    <box frame="4218" keyframe="0" outside="0" occluded="0" xtl="810.80" ytl="92.60" xbr="1316.00" ybr="1080.00" z_order="0">
    </box>
    <box frame="4219" keyframe="0" outside="0" occluded="0" xtl="810.80" ytl="92.60" xbr="1316.00" ybr="1080.00" z_order="0">
    </box>
    <box frame="4220" keyframe="0" outside="0" occluded="0" xtl="810.80" ytl="92.60" xbr="1316.00" ybr="1080.00" z_order="0">
    </box>
    <box frame="4221" keyframe="0" outside="0" occluded="0" xtl="810.80" ytl="92.60" xbr="1316.00" ybr="1080.00" z_order="0">
    </box>
    <box frame="4222" keyframe="0" outside="0" occluded="0" xtl="810.80" ytl="92.60" xbr="1316.00" ybr="1080.00" z_order="0">
    </box>
    <box frame="4223" keyframe="0" outside="0" occluded="0" xtl="810.80" ytl="92.60" xbr="1316.00" ybr="1080.00" z_order="0">
    </box>
    <box frame="4224" keyframe="1" outside="1" occluded="0" xtl="810.80" ytl="92.60" xbr="1316.00" ybr="1080.00" z_order="0">
    </box>
  </track>
</annotations>
